ASurveyOnDialogueSystemsRecentAdvancesAndNewFrontiersFanyi/README.md
ASurveyOnDialogueSystemsRecentAdvancesAndNewFrontiersFanyi/__init__.py
ASurveyOnDialogueSystemsRecentAdvancesAndNewFrontiersFanyi/__main__.py
ASurveyOnDialogueSystemsRecentAdvancesAndNewFrontiersFanyi/file.pdf
ASurveyOnDialogueSystemsRecentAdvancesAndNewFrontiersFanyi/index.html
a_survey_on_dialogue_systems_recent_advances_and_new_frontiers_fanyi-2024.3.4.0.dist-info/METADATA
a_survey_on_dialogue_systems_recent_advances_and_new_frontiers_fanyi-2024.3.4.0.dist-info/WHEEL
a_survey_on_dialogue_systems_recent_advances_and_new_frontiers_fanyi-2024.3.4.0.dist-info/entry_points.txt
a_survey_on_dialogue_systems_recent_advances_and_new_frontiers_fanyi-2024.3.4.0.dist-info/top_level.txt
a_survey_on_dialogue_systems_recent_advances_and_new_frontiers_fanyi-2024.3.4.0.dist-info/RECORD
